easy/__init__.py
easy/helper.py
easy/models.py
easy/tests.py
easy/util.py
easy/admin/__init__.py
easy/admin/decorators.py
easy/admin/field.py
easy/admin/mixin.py
test_app/migrations/0001_initial.py
test_app/migrations/0002_auto_20240827_1315.py
test_app/migrations/__init__.py
django_admin_easy-0.8.0.dist-info/LICENSE.md
django_admin_easy-0.8.0.dist-info/METADATA
django_admin_easy-0.8.0.dist-info/WHEEL
django_admin_easy-0.8.0.dist-info/top_level.txt
django_admin_easy-0.8.0.dist-info/RECORD
