Metadata-Version: 2.1
Name: django-admin-easy
Version: 0.8.0
Summary: Collection of admin fields and decorators to help to create computed or custom fields more friendly and easy way
Home-page: http://github.com/ebertti/django-admin-easy/
Author: Ezequiel Bertti
Author-email: ebertti@gmail.com
License: MIT License
Keywords: admin field django easy simple
Platform: OS Independent
Classifier: Development Status :: 5 - Production/Stable
Classifier: Framework :: Django
Classifier: Intended Audience :: Developers
Classifier: License :: OSI Approved :: MIT License
Classifier: Natural Language :: English
Classifier: Natural Language :: Portuguese (Brazilian)
Classifier: Operating System :: OS Independent
Classifier: Programming Language :: Python :: 3
Classifier: Programming Language :: Python :: 3.7
Classifier: Programming Language :: Python :: 3.8
Classifier: Programming Language :: Python :: 3.9
Classifier: Programming Language :: Python :: 3.10
Classifier: Programming Language :: Python :: 3.11
Classifier: Programming Language :: Python :: 3.12
License-File: LICENSE.md
Requires-Dist: django
